{
  "strategy_id": "MR_001831",
  "created_at": "2026-03-10T12:17:03.269202",
  "updated_at": "2026-03-10T12:17:03.274200",
  "asset": "JB1 Comdty",
  "strategy_type": "mean_reversion",
  "strategy_name": "spread_zscore_reversion",
  "params": {
    "period": 20,
    "entry_threshold": 1.0,
    "exit_threshold": 0.5
  },
  "related_asset": "TY1 Comdty",
  "performance": {
    "sharpe_3y": 1.9836855957596682,
    "sharpe_6m": 2.635689635713616,
    "sharpe_1m": 4.121935792004204,
    "total_return": 0.18647891324765467,
    "annual_return": 0.0,
    "max_drawdown": 0.03404561022411859,
    "win_rate": 0.6470588235294117,
    "num_trades": 120,
    "calmar_ratio": 1.470006454757103,
    "sortino_ratio": 3.1194636283545645
  },
  "is_active": true,
  "version": 1
}