{
  "strategy_id": "MR_001838",
  "created_at": "2026-03-10T12:49:40.156225",
  "updated_at": "2026-03-10T12:49:40.161229",
  "asset": "JB1 Comdty",
  "strategy_type": "mean_reversion",
  "strategy_name": "spread_zscore_reversion",
  "params": {
    "period": 30,
    "entry_threshold": 1.5,
    "exit_threshold": 0.0
  },
  "related_asset": "TY1 Comdty",
  "performance": {
    "sharpe_3y": 1.1183475028093561,
    "sharpe_6m": 1.5991186637668249,
    "sharpe_1m": -1.0081997683040202,
    "total_return": 0.156246512564568,
    "annual_return": 0.0,
    "max_drawdown": 0.04323221455480449,
    "win_rate": 0.6545454545454545,
    "num_trades": 56,
    "calmar_ratio": 0.847855532461179,
    "sortino_ratio": 2.0489197970102238
  },
  "is_active": true,
  "version": 1
}