{
  "strategy_id": "MOM_000063",
  "created_at": "2026-02-09T15:24:22.043145",
  "updated_at": "2026-02-09T15:24:22.058948",
  "asset": "GJGB10 Index",
  "strategy_type": "momentum",
  "strategy_name": "rate_of_change",
  "params": {
    "period": 10,
    "entry_threshold": 0,
    "exit_threshold": 0
  },
  "related_asset": null,
  "performance": {
    "sharpe_3y": 1.4473912255061296,
    "sharpe_6m": 2.980959041222342,
    "sharpe_1m": 1.9473605157630711,
    "total_return": 0.09603596120941305,
    "annual_return": 0.0,
    "max_drawdown": 0.04419369891735539,
    "win_rate": 0.3130434782608696,
    "num_trades": 115,
    "calmar_ratio": 0.48076420245209506,
    "sortino_ratio": 1.1808176792100138
  },
  "is_active": true,
  "version": 1
}