{
  "strategy_id": "MR_002027",
  "created_at": "2026-02-19T13:18:42.967808",
  "updated_at": "2026-02-19T13:18:42.979834",
  "asset": "GDBR2 Index",
  "strategy_type": "mean_reversion",
  "strategy_name": "spread_percentile_reversion",
  "params": {
    "period": 20,
    "low_percentile": 20,
    "high_percentile": 90,
    "exit_percentile": 50
  },
  "related_asset": "USGG2YR Index",
  "performance": {
    "sharpe_3y": 1.1480268001054432,
    "sharpe_6m": -0.777170595395426,
    "sharpe_1m": 0.8092300396302916,
    "total_return": 0.3916332458357354,
    "annual_return": 0.0,
    "max_drawdown": 0.12924281618386846,
    "win_rate": 0.5754716981132075,
    "num_trades": 107,
    "calmar_ratio": 0.6058745865163117,
    "sortino_ratio": 1.4265247773943937
  },
  "is_active": true,
  "version": 1
}