{
  "strategies": {
    "MOM_000010": {
      "file": "MOM_000010.json",
      "asset": "GVSK10YR Index",
      "strategy_type": "momentum",
      "sharpe_3y": 1.2944824667771293,
      "sharpe_6m": -0.0021506179444643497,
      "is_active": true,
      "updated_at": "2026-03-10T12:04:56.650138"
    },
    "MOM_000011": {
      "file": "MOM_000011.json",
      "asset": "GVSK10YR Index",
      "strategy_type": "momentum",
      "sharpe_3y": 1.3682153022478636,
      "sharpe_6m": -0.9420887562227394,
      "is_active": true,
      "updated_at": "2026-03-10T12:04:56.659136"
    },
    "MOM_000013": {
      "file": "MOM_000013.json",
      "asset": "GVSK10YR Index",
      "strategy_type": "momentum",
      "sharpe_3y": 1.2745993242509888,
      "sharpe_6m": -0.10077456964224729,
      "is_active": true,
      "updated_at": "2026-03-10T12:04:56.670136"
    },
    "MOM_000014": {
      "file": "MOM_000014.json",
      "asset": "GVSK10YR Index",
      "strategy_type": "momentum",
      "sharpe_3y": 1.4018071495130096,
      "sharpe_6m": 0.8137653474525667,
      "is_active": true,
      "updated_at": "2026-03-10T12:04:56.678137"
    },
    "MOM_000076": {
      "file": "MOM_000076.json",
      "asset": "GVSK3YR Index",
      "strategy_type": "momentum",
      "sharpe_3y": 1.2754757209289953,
      "sharpe_6m": -0.9435271271698732,
      "is_active": true,
      "updated_at": "2026-03-10T12:04:56.689136"
    },
    "MOM_000077": {
      "file": "MOM_000077.json",
      "asset": "GVSK3YR Index",
      "strategy_type": "momentum",
      "sharpe_3y": 1.2627656008548773,
      "sharpe_6m": -0.04854532043506432,
      "is_active": true,
      "updated_at": "2026-03-10T12:04:56.699138"
    },
    "MOM_000078": {
      "file": "MOM_000078.json",
      "asset": "GVSK3YR Index",
      "strategy_type": "momentum",
      "sharpe_3y": 1.1632456744763682,
      "sharpe_6m": -0.5167225900265903,
      "is_active": true,
      "updated_at": "2026-03-10T12:04:56.707136"
    },
    "MOM_000079": {
      "file": "MOM_000079.json",
      "asset": "GVSK3YR Index",
      "strategy_type": "momentum",
      "sharpe_3y": 1.4651473369277093,
      "sharpe_6m": 0.9136835058977343,
      "is_active": true,
      "updated_at": "2026-03-10T12:04:56.715137"
    },
    "MOM_000102": {
      "file": "MOM_000102.json",
      "asset": "GVSK10YR Index",
      "strategy_type": "momentum",
      "sharpe_3y": 1.1292628297838896,
      "sharpe_6m": -0.8648826585017201,
      "is_active": true,
      "updated_at": "2026-03-10T12:04:56.722135"
    },
    "MOM_000103": {
      "file": "MOM_000103.json",
      "asset": "GVSK10YR Index",
      "strategy_type": "momentum",
      "sharpe_3y": 1.0808261386194855,
      "sharpe_6m": -1.025293225555412,
      "is_active": true,
      "updated_at": "2026-03-10T12:04:56.730136"
    },
    "MOM_000104": {
      "file": "MOM_000104.json",
      "asset": "GVSK10YR Index",
      "strategy_type": "momentum",
      "sharpe_3y": 1.1045372179692665,
      "sharpe_6m": -0.30750811135164957,
      "is_active": true,
      "updated_at": "2026-03-10T12:04:56.737135"
    },
    "MOM_000106": {
      "file": "MOM_000106.json",
      "asset": "GVSK10YR Index",
      "strategy_type": "momentum",
      "sharpe_3y": 1.0139187698040952,
      "sharpe_6m": -0.6852674082299206,
      "is_active": true,
      "updated_at": "2026-03-10T12:04:56.748137"
    },
    "MOM_000180": {
      "file": "MOM_000180.json",
      "asset": "GVSK3YR Index",
      "strategy_type": "momentum",
      "sharpe_3y": 1.2912610152919863,
      "sharpe_6m": -0.6625359327465498,
      "is_active": true,
      "updated_at": "2026-03-10T12:04:56.758137"
    },
    "MOM_000181": {
      "file": "MOM_000181.json",
      "asset": "GVSK3YR Index",
      "strategy_type": "momentum",
      "sharpe_3y": 1.4622236924436485,
      "sharpe_6m": -0.7261381530486992,
      "is_active": true,
      "updated_at": "2026-03-10T12:04:56.767135"
    },
    "MOM_000182": {
      "file": "MOM_000182.json",
      "asset": "GVSK3YR Index",
      "strategy_type": "momentum",
      "sharpe_3y": 1.3877141172271465,
      "sharpe_6m": -0.7912657816477803,
      "is_active": true,
      "updated_at": "2026-03-10T12:04:56.777136"
    },
    "MOM_000205": {
      "file": "MOM_000205.json",
      "asset": "GVSK10YR Index",
      "strategy_type": "momentum",
      "sharpe_3y": 1.3121369591689884,
      "sharpe_6m": -0.2841738937998053,
      "is_active": true,
      "updated_at": "2026-03-10T12:04:56.785136"
    },
    "MOM_000206": {
      "file": "MOM_000206.json",
      "asset": "GVSK10YR Index",
      "strategy_type": "momentum",
      "sharpe_3y": 1.2658093812129232,
      "sharpe_6m": -0.19098686614428872,
      "is_active": true,
      "updated_at": "2026-03-10T12:04:56.793136"
    },
    "MOM_000244": {
      "file": "MOM_000244.json",
      "asset": "GVSK3YR Index",
      "strategy_type": "momentum",
      "sharpe_3y": 1.3667157433567858,
      "sharpe_6m": -0.16408593686751857,
      "is_active": true,
      "updated_at": "2026-03-10T12:04:56.803138"
    },
    "MOM_000245": {
      "file": "MOM_000245.json",
      "asset": "GVSK3YR Index",
      "strategy_type": "momentum",
      "sharpe_3y": 1.2551263055927981,
      "sharpe_6m": -0.8624732926461929,
      "is_active": true,
      "updated_at": "2026-03-10T12:04:56.812139"
    },
    "MOM_000662": {
      "file": "MOM_000662.json",
      "asset": "GVSK3YR Index",
      "strategy_type": "momentum",
      "sharpe_3y": 1.0828725010837803,
      "sharpe_6m": -0.6915417913853309,
      "is_active": true,
      "updated_at": "2026-03-10T12:04:56.822137"
    },
    "MOM_000665": {
      "file": "MOM_000665.json",
      "asset": "GVSK3YR Index",
      "strategy_type": "momentum",
      "sharpe_3y": 1.190449817846772,
      "sharpe_6m": -0.9001113014541103,
      "is_active": true,
      "updated_at": "2026-03-10T12:04:56.830138"
    },
    "MOM_000668": {
      "file": "MOM_000668.json",
      "asset": "GVSK3YR Index",
      "strategy_type": "momentum",
      "sharpe_3y": 1.0530556587896216,
      "sharpe_6m": -1.2758525213530942,
      "is_active": true,
      "updated_at": "2026-03-10T12:04:56.839135"
    },
    "MOM_000670": {
      "file": "MOM_000670.json",
      "asset": "GVSK3YR Index",
      "strategy_type": "momentum",
      "sharpe_3y": 1.0350536328584325,
      "sharpe_6m": -0.84745873250334,
      "is_active": true,
      "updated_at": "2026-03-10T12:04:56.848138"
    },
    "MOM_000671": {
      "file": "MOM_000671.json",
      "asset": "GVSK3YR Index",
      "strategy_type": "momentum",
      "sharpe_3y": 1.2768388113483706,
      "sharpe_6m": -1.5679370900856364,
      "is_active": true,
      "updated_at": "2026-03-10T12:04:56.856136"
    },
    "MOM_000673": {
      "file": "MOM_000673.json",
      "asset": "GVSK3YR Index",
      "strategy_type": "momentum",
      "sharpe_3y": 1.0294805786108632,
      "sharpe_6m": -0.7140745086669319,
      "is_active": true,
      "updated_at": "2026-03-10T12:04:56.865136"
    },
    "MOM_000674": {
      "file": "MOM_000674.json",
      "asset": "GVSK3YR Index",
      "strategy_type": "momentum",
      "sharpe_3y": 1.5288971761247547,
      "sharpe_6m": -1.588766225069431,
      "is_active": true,
      "updated_at": "2026-03-10T12:04:56.872135"
    },
    "MOM_000675": {
      "file": "MOM_000675.json",
      "asset": "GVSK3YR Index",
      "strategy_type": "momentum",
      "sharpe_3y": 1.0282517638661985,
      "sharpe_6m": -0.183408269905869,
      "is_active": true,
      "updated_at": "2026-03-10T12:04:56.881140"
    },
    "MOM_000676": {
      "file": "MOM_000676.json",
      "asset": "GVSK3YR Index",
      "strategy_type": "momentum",
      "sharpe_3y": 1.0217997114485402,
      "sharpe_6m": -0.6810264197293407,
      "is_active": true,
      "updated_at": "2026-03-10T12:04:56.888135"
    },
    "MOM_000677": {
      "file": "MOM_000677.json",
      "asset": "GVSK3YR Index",
      "strategy_type": "momentum",
      "sharpe_3y": 1.106513263373337,
      "sharpe_6m": -1.5755657632165414,
      "is_active": true,
      "updated_at": "2026-03-10T12:04:56.898136"
    },
    "MOM_000678": {
      "file": "MOM_000678.json",
      "asset": "GVSK3YR Index",
      "strategy_type": "momentum",
      "sharpe_3y": 1.118624758908262,
      "sharpe_6m": -0.4342833172943111,
      "is_active": true,
      "updated_at": "2026-03-10T12:04:56.905136"
    },
    "MOM_000679": {
      "file": "MOM_000679.json",
      "asset": "GVSK3YR Index",
      "strategy_type": "momentum",
      "sharpe_3y": 1.2919260739179168,
      "sharpe_6m": -1.3228870133694992,
      "is_active": true,
      "updated_at": "2026-03-10T12:04:56.915137"
    },
    "MOM_000680": {
      "file": "MOM_000680.json",
      "asset": "GVSK3YR Index",
      "strategy_type": "momentum",
      "sharpe_3y": 1.5099712550525937,
      "sharpe_6m": -1.7762951419309907,
      "is_active": true,
      "updated_at": "2026-03-10T12:04:56.923136"
    },
    "MOM_000681": {
      "file": "MOM_000681.json",
      "asset": "GVSK3YR Index",
      "strategy_type": "momentum",
      "sharpe_3y": 1.1217871181133283,
      "sharpe_6m": -0.5472530232507574,
      "is_active": true,
      "updated_at": "2026-03-10T12:04:56.933136"
    },
    "MOM_000682": {
      "file": "MOM_000682.json",
      "asset": "GVSK3YR Index",
      "strategy_type": "momentum",
      "sharpe_3y": 1.3419395772242926,
      "sharpe_6m": -1.3451310689526341,
      "is_active": true,
      "updated_at": "2026-03-10T12:04:56.941136"
    },
    "MOM_000683": {
      "file": "MOM_000683.json",
      "asset": "GVSK3YR Index",
      "strategy_type": "momentum",
      "sharpe_3y": 1.4906453911569433,
      "sharpe_6m": -1.5699337985190611,
      "is_active": true,
      "updated_at": "2026-03-10T12:04:56.950135"
    },
    "MOM_000748": {
      "file": "MOM_000748.json",
      "asset": "GVSK10YR Index",
      "strategy_type": "momentum",
      "sharpe_3y": 1.128522264900014,
      "sharpe_6m": 0.1797926151057576,
      "is_active": true,
      "updated_at": "2026-03-10T12:04:56.958135"
    },
    "MOM_000749": {
      "file": "MOM_000749.json",
      "asset": "GVSK10YR Index",
      "strategy_type": "momentum",
      "sharpe_3y": 1.0547305578028394,
      "sharpe_6m": -0.17048745140536295,
      "is_active": true,
      "updated_at": "2026-03-10T12:04:56.967135"
    },
    "MOM_000800": {
      "file": "MOM_000800.json",
      "asset": "GVSK3YR Index",
      "strategy_type": "momentum",
      "sharpe_3y": 1.272407627390252,
      "sharpe_6m": 0.3974088355675384,
      "is_active": true,
      "updated_at": "2026-03-10T12:04:56.976136"
    },
    "MOM_000801": {
      "file": "MOM_000801.json",
      "asset": "GVSK3YR Index",
      "strategy_type": "momentum",
      "sharpe_3y": 1.256710909797132,
      "sharpe_6m": -0.04213703891263327,
      "is_active": true,
      "updated_at": "2026-03-10T12:04:56.987136"
    },
    "MOM_000877": {
      "file": "MOM_000877.json",
      "asset": "GVSK10YR Index",
      "strategy_type": "momentum",
      "sharpe_3y": 1.2334748049900814,
      "sharpe_6m": 0.41907199628887964,
      "is_active": true,
      "updated_at": "2026-03-10T12:04:56.996140"
    },
    "MOM_000916": {
      "file": "MOM_000916.json",
      "asset": "GVSK3YR Index",
      "strategy_type": "momentum",
      "sharpe_3y": 1.4451542887776108,
      "sharpe_6m": -0.31670298220006965,
      "is_active": true,
      "updated_at": "2026-03-10T12:04:57.007136"
    },
    "MR_001595": {
      "file": "MR_001595.json",
      "asset": "TY1 Comdty",
      "strategy_type": "mean_reversion",
      "sharpe_3y": 1.1424668006857726,
      "sharpe_6m": -2.0339926559150867,
      "is_active": true,
      "updated_at": "2026-03-10T12:05:53.394210"
    },
    "MR_001768": {
      "file": "MR_001768.json",
      "asset": "GVSK3YR Index",
      "strategy_type": "mean_reversion",
      "sharpe_3y": 1.2984696107964606,
      "sharpe_6m": 1.5376333669300732,
      "is_active": true,
      "updated_at": "2026-03-10T12:05:53.406211"
    },
    "MR_001824": {
      "file": "MR_001824.json",
      "asset": "JB1 Comdty",
      "strategy_type": "mean_reversion",
      "sharpe_3y": 2.446155230360093,
      "sharpe_6m": 2.1007968947790636,
      "is_active": true,
      "updated_at": "2026-03-10T12:05:53.415210"
    },
    "MR_001825": {
      "file": "MR_001825.json",
      "asset": "JB1 Comdty",
      "strategy_type": "mean_reversion",
      "sharpe_3y": 2.545764513786035,
      "sharpe_6m": 2.0901694304876557,
      "is_active": true,
      "updated_at": "2026-03-10T12:05:53.425209"
    },
    "MR_001826": {
      "file": "MR_001826.json",
      "asset": "JB1 Comdty",
      "strategy_type": "mean_reversion",
      "sharpe_3y": 2.255489079778586,
      "sharpe_6m": 1.6412435748317857,
      "is_active": true,
      "updated_at": "2026-03-10T12:05:53.436210"
    },
    "MR_001827": {
      "file": "MR_001827.json",
      "asset": "JB1 Comdty",
      "strategy_type": "mean_reversion",
      "sharpe_3y": 2.5360584664689725,
      "sharpe_6m": 1.8521006852767679,
      "is_active": true,
      "updated_at": "2026-03-10T12:05:53.444209"
    },
    "MR_001828": {
      "file": "MR_001828.json",
      "asset": "JB1 Comdty",
      "strategy_type": "mean_reversion",
      "sharpe_3y": 1.7930456642574917,
      "sharpe_6m": 2.147296946580623,
      "is_active": true,
      "updated_at": "2026-03-10T12:05:53.455210"
    },
    "MR_001829": {
      "file": "MR_001829.json",
      "asset": "JB1 Comdty",
      "strategy_type": "mean_reversion",
      "sharpe_3y": 1.7766573056967583,
      "sharpe_6m": 2.147296946580625,
      "is_active": true,
      "updated_at": "2026-03-10T12:05:53.464210"
    },
    "MR_001830": {
      "file": "MR_001830.json",
      "asset": "JB1 Comdty",
      "strategy_type": "mean_reversion",
      "sharpe_3y": 1.5241426175691193,
      "sharpe_6m": 0.9412388376902988,
      "is_active": true,
      "updated_at": "2026-03-10T12:05:53.473208"
    },
    "MR_001831": {
      "file": "MR_001831.json",
      "asset": "JB1 Comdty",
      "strategy_type": "mean_reversion",
      "sharpe_3y": 1.7915972789438033,
      "sharpe_6m": 1.144110619293932,
      "is_active": true,
      "updated_at": "2026-03-10T12:05:53.484210"
    },
    "MR_001832": {
      "file": "MR_001832.json",
      "asset": "JB1 Comdty",
      "strategy_type": "mean_reversion",
      "sharpe_3y": 1.41186965541512,
      "sharpe_6m": 0.9358102345671678,
      "is_active": true,
      "updated_at": "2026-03-10T12:05:53.492209"
    },
    "MR_001833": {
      "file": "MR_001833.json",
      "asset": "JB1 Comdty",
      "strategy_type": "mean_reversion",
      "sharpe_3y": 1.8082379660197312,
      "sharpe_6m": 1.0835987505168332,
      "is_active": true,
      "updated_at": "2026-03-10T12:05:53.503209"
    },
    "MR_001834": {
      "file": "MR_001834.json",
      "asset": "JB1 Comdty",
      "strategy_type": "mean_reversion",
      "sharpe_3y": 1.4258105071733072,
      "sharpe_6m": 1.7373543241294516,
      "is_active": true,
      "updated_at": "2026-03-10T12:05:53.518210"
    },
    "MR_001835": {
      "file": "MR_001835.json",
      "asset": "JB1 Comdty",
      "strategy_type": "mean_reversion",
      "sharpe_3y": 1.5120308853177498,
      "sharpe_6m": 1.790938674626312,
      "is_active": true,
      "updated_at": "2026-03-10T12:05:53.526210"
    },
    "MR_001836": {
      "file": "MR_001836.json",
      "asset": "JB1 Comdty",
      "strategy_type": "mean_reversion",
      "sharpe_3y": 1.3957219634949958,
      "sharpe_6m": 0.2539805305840516,
      "is_active": true,
      "updated_at": "2026-03-10T12:05:53.536209"
    },
    "MR_001837": {
      "file": "MR_001837.json",
      "asset": "JB1 Comdty",
      "strategy_type": "mean_reversion",
      "sharpe_3y": 1.6490572491227788,
      "sharpe_6m": 1.4793504074044939,
      "is_active": true,
      "updated_at": "2026-03-10T12:05:53.544210"
    },
    "MR_001838": {
      "file": "MR_001838.json",
      "asset": "JB1 Comdty",
      "strategy_type": "mean_reversion",
      "sharpe_3y": 1.290028243763219,
      "sharpe_6m": 0.6381056114978987,
      "is_active": true,
      "updated_at": "2026-03-10T12:05:53.553209"
    },
    "MR_001839": {
      "file": "MR_001839.json",
      "asset": "JB1 Comdty",
      "strategy_type": "mean_reversion",
      "sharpe_3y": 1.533514715796813,
      "sharpe_6m": 1.6290827685420215,
      "is_active": true,
      "updated_at": "2026-03-10T12:05:53.563210"
    },
    "MR_001840": {
      "file": "MR_001840.json",
      "asset": "JB1 Comdty",
      "strategy_type": "mean_reversion",
      "sharpe_3y": 1.0752998887191905,
      "sharpe_6m": 0.6872165113900172,
      "is_active": true,
      "updated_at": "2026-03-10T12:05:53.573213"
    },
    "MR_001841": {
      "file": "MR_001841.json",
      "asset": "JB1 Comdty",
      "strategy_type": "mean_reversion",
      "sharpe_3y": 1.2962596081082267,
      "sharpe_6m": 1.8215350761842493,
      "is_active": true,
      "updated_at": "2026-03-10T12:05:53.582209"
    },
    "MR_002184": {
      "file": "MR_002184.json",
      "asset": "JB1 Comdty",
      "strategy_type": "mean_reversion",
      "sharpe_3y": 1.3088204389030265,
      "sharpe_6m": 0.9388674236016757,
      "is_active": true,
      "updated_at": "2026-03-10T12:06:49.058281"
    },
    "MR_002185": {
      "file": "MR_002185.json",
      "asset": "JB1 Comdty",
      "strategy_type": "mean_reversion",
      "sharpe_3y": 1.3749394484372737,
      "sharpe_6m": 1.1074251812156446,
      "is_active": true,
      "updated_at": "2026-03-10T12:06:49.069281"
    },
    "MR_002186": {
      "file": "MR_002186.json",
      "asset": "JB1 Comdty",
      "strategy_type": "mean_reversion",
      "sharpe_3y": 1.3330092151888466,
      "sharpe_6m": 0.8018504938445027,
      "is_active": true,
      "updated_at": "2026-03-10T12:06:49.081281"
    },
    "MR_002187": {
      "file": "MR_002187.json",
      "asset": "JB1 Comdty",
      "strategy_type": "mean_reversion",
      "sharpe_3y": 1.389088792890717,
      "sharpe_6m": 1.240787083944814,
      "is_active": true,
      "updated_at": "2026-03-10T12:06:49.093282"
    },
    "MR_002188": {
      "file": "MR_002188.json",
      "asset": "JB1 Comdty",
      "strategy_type": "mean_reversion",
      "sharpe_3y": 1.4545307383236872,
      "sharpe_6m": 1.4109148531434923,
      "is_active": true,
      "updated_at": "2026-03-10T12:06:49.106285"
    },
    "MR_002189": {
      "file": "MR_002189.json",
      "asset": "JB1 Comdty",
      "strategy_type": "mean_reversion",
      "sharpe_3y": 1.4145449940137595,
      "sharpe_6m": 1.109154450864317,
      "is_active": true,
      "updated_at": "2026-03-10T12:06:49.120283"
    },
    "MR_002190": {
      "file": "MR_002190.json",
      "asset": "JB1 Comdty",
      "strategy_type": "mean_reversion",
      "sharpe_3y": 1.4432402371148307,
      "sharpe_6m": 1.0508616054519073,
      "is_active": true,
      "updated_at": "2026-03-10T12:06:49.134284"
    },
    "MR_002191": {
      "file": "MR_002191.json",
      "asset": "JB1 Comdty",
      "strategy_type": "mean_reversion",
      "sharpe_3y": 1.508485430789319,
      "sharpe_6m": 1.2170364026543392,
      "is_active": true,
      "updated_at": "2026-03-10T12:06:49.147285"
    },
    "MR_002192": {
      "file": "MR_002192.json",
      "asset": "JB1 Comdty",
      "strategy_type": "mean_reversion",
      "sharpe_3y": 1.4697972937934074,
      "sharpe_6m": 0.9177668164605295,
      "is_active": true,
      "updated_at": "2026-03-10T12:06:49.161283"
    },
    "MR_002196": {
      "file": "MR_002196.json",
      "asset": "JB1 Comdty",
      "strategy_type": "mean_reversion",
      "sharpe_3y": 1.04258531875351,
      "sharpe_6m": 0.388904456406798,
      "is_active": true,
      "updated_at": "2026-03-10T12:06:49.176283"
    },
    "MR_002197": {
      "file": "MR_002197.json",
      "asset": "JB1 Comdty",
      "strategy_type": "mean_reversion",
      "sharpe_3y": 1.0374301012600748,
      "sharpe_6m": 0.5208730885461816,
      "is_active": true,
      "updated_at": "2026-03-10T12:06:49.194284"
    },
    "MR_002199": {
      "file": "MR_002199.json",
      "asset": "JB1 Comdty",
      "strategy_type": "mean_reversion",
      "sharpe_3y": 1.0963844471699296,
      "sharpe_6m": 0.38555084207918117,
      "is_active": true,
      "updated_at": "2026-03-10T12:06:49.208282"
    },
    "MR_002200": {
      "file": "MR_002200.json",
      "asset": "JB1 Comdty",
      "strategy_type": "mean_reversion",
      "sharpe_3y": 1.0913176387797516,
      "sharpe_6m": 0.5162461872985792,
      "is_active": true,
      "updated_at": "2026-03-10T12:06:49.221282"
    },
    "ADV_002292": {
      "file": "ADV_002292.json",
      "asset": "GVSK10YR Index",
      "strategy_type": "advanced",
      "sharpe_3y": 1.0155425033477157,
      "sharpe_6m": 0.4345465970491003,
      "is_active": true,
      "updated_at": "2026-03-10T12:06:49.235282"
    },
    "ADV_002293": {
      "file": "ADV_002293.json",
      "asset": "GVSK10YR Index",
      "strategy_type": "advanced",
      "sharpe_3y": 1.0328021199709652,
      "sharpe_6m": 0.34872264057648616,
      "is_active": true,
      "updated_at": "2026-03-10T12:06:49.249286"
    },
    "ADV_002296": {
      "file": "ADV_002296.json",
      "asset": "GVSK10YR Index",
      "strategy_type": "advanced",
      "sharpe_3y": 1.4597573352118665,
      "sharpe_6m": -0.0568070398850372,
      "is_active": true,
      "updated_at": "2026-03-10T12:06:49.264285"
    },
    "ADV_002299": {
      "file": "ADV_002299.json",
      "asset": "GVSK10YR Index",
      "strategy_type": "advanced",
      "sharpe_3y": 1.1990025551890418,
      "sharpe_6m": -0.17871686101611153,
      "is_active": true,
      "updated_at": "2026-03-10T12:06:49.283285"
    },
    "ADV_002300": {
      "file": "ADV_002300.json",
      "asset": "GVSK10YR Index",
      "strategy_type": "advanced",
      "sharpe_3y": 1.1742100223554985,
      "sharpe_6m": -0.6440432250068232,
      "is_active": true,
      "updated_at": "2026-03-10T12:06:49.299284"
    },
    "ADV_002526": {
      "file": "ADV_002526.json",
      "asset": "GVSK3YR Index",
      "strategy_type": "advanced",
      "sharpe_3y": 1.3479864134088555,
      "sharpe_6m": 1.1012727997932368,
      "is_active": true,
      "updated_at": "2026-03-10T12:06:49.320284"
    },
    "ADV_002527": {
      "file": "ADV_002527.json",
      "asset": "GVSK3YR Index",
      "strategy_type": "advanced",
      "sharpe_3y": 1.3321542003167657,
      "sharpe_6m": 1.0293464706503814,
      "is_active": true,
      "updated_at": "2026-03-10T12:06:49.336285"
    },
    "ADV_002528": {
      "file": "ADV_002528.json",
      "asset": "GVSK3YR Index",
      "strategy_type": "advanced",
      "sharpe_3y": 1.3813303942357849,
      "sharpe_6m": 0.6694151461423663,
      "is_active": true,
      "updated_at": "2026-03-10T12:06:49.351284"
    },
    "ADV_002529": {
      "file": "ADV_002529.json",
      "asset": "GVSK3YR Index",
      "strategy_type": "advanced",
      "sharpe_3y": 1.2669305464840965,
      "sharpe_6m": -0.5446757794164944,
      "is_active": true,
      "updated_at": "2026-03-10T12:06:49.368285"
    },
    "ADV_002530": {
      "file": "ADV_002530.json",
      "asset": "GVSK3YR Index",
      "strategy_type": "advanced",
      "sharpe_3y": 1.453782717744965,
      "sharpe_6m": -0.018922789421382615,
      "is_active": true,
      "updated_at": "2026-03-10T12:06:49.383284"
    },
    "ADV_002531": {
      "file": "ADV_002531.json",
      "asset": "GVSK3YR Index",
      "strategy_type": "advanced",
      "sharpe_3y": 1.5337406353353589,
      "sharpe_6m": -0.28526029234688227,
      "is_active": true,
      "updated_at": "2026-03-10T12:06:49.397290"
    },
    "ADV_002533": {
      "file": "ADV_002533.json",
      "asset": "GVSK3YR Index",
      "strategy_type": "advanced",
      "sharpe_3y": 1.4232314905592252,
      "sharpe_6m": -0.378494481083325,
      "is_active": true,
      "updated_at": "2026-03-10T12:06:49.410283"
    },
    "ADV_002534": {
      "file": "ADV_002534.json",
      "asset": "GVSK3YR Index",
      "strategy_type": "advanced",
      "sharpe_3y": 1.5071482569526813,
      "sharpe_6m": -0.39221399952177227,
      "is_active": true,
      "updated_at": "2026-03-10T12:06:49.423283"
    },
    "ADV_002537": {
      "file": "ADV_002537.json",
      "asset": "GVSK3YR Index",
      "strategy_type": "advanced",
      "sharpe_3y": 1.1879805818731703,
      "sharpe_6m": 1.1322608500411797,
      "is_active": true,
      "updated_at": "2026-03-10T12:06:49.435282"
    },
    "ADV_002540": {
      "file": "ADV_002540.json",
      "asset": "GVSK3YR Index",
      "strategy_type": "advanced",
      "sharpe_3y": 1.1885032083268896,
      "sharpe_6m": -0.2852602923468752,
      "is_active": true,
      "updated_at": "2026-03-10T12:06:49.448285"
    },
    "ADV_002543": {
      "file": "ADV_002543.json",
      "asset": "GVSK3YR Index",
      "strategy_type": "advanced",
      "sharpe_3y": 1.2143612633130136,
      "sharpe_6m": -0.3922139995217809,
      "is_active": true,
      "updated_at": "2026-03-10T12:06:49.462284"
    },
    "ADV_002690": {
      "file": "ADV_002690.json",
      "asset": "GVSK3YR Index",
      "strategy_type": "advanced",
      "sharpe_3y": 1.0895085830411584,
      "sharpe_6m": -1.0493402340513096,
      "is_active": true,
      "updated_at": "2026-03-10T12:06:49.475282"
    },
    "ADV_002691": {
      "file": "ADV_002691.json",
      "asset": "GVSK3YR Index",
      "strategy_type": "advanced",
      "sharpe_3y": 1.3694179126246118,
      "sharpe_6m": 0.029970705298120112,
      "is_active": true,
      "updated_at": "2026-03-10T12:06:49.488283"
    },
    "ADV_002692": {
      "file": "ADV_002692.json",
      "asset": "GVSK3YR Index",
      "strategy_type": "advanced",
      "sharpe_3y": 1.397745580578203,
      "sharpe_6m": -0.5100129633780112,
      "is_active": true,
      "updated_at": "2026-03-10T12:06:49.502285"
    },
    "ADV_002693": {
      "file": "ADV_002693.json",
      "asset": "GVSK3YR Index",
      "strategy_type": "advanced",
      "sharpe_3y": 1.4048968314597576,
      "sharpe_6m": -0.6032084733426031,
      "is_active": true,
      "updated_at": "2026-03-10T12:06:49.516282"
    },
    "ADV_002694": {
      "file": "ADV_002694.json",
      "asset": "GVSK3YR Index",
      "strategy_type": "advanced",
      "sharpe_3y": 1.4520589191012956,
      "sharpe_6m": 0.5960707729169991,
      "is_active": true,
      "updated_at": "2026-03-10T12:06:49.527284"
    },
    "ADV_002695": {
      "file": "ADV_002695.json",
      "asset": "GVSK3YR Index",
      "strategy_type": "advanced",
      "sharpe_3y": 1.3945986620431192,
      "sharpe_6m": 0.3122115116920586,
      "is_active": true,
      "updated_at": "2026-03-10T12:06:49.539282"
    },
    "ADV_002696": {
      "file": "ADV_002696.json",
      "asset": "GVSK3YR Index",
      "strategy_type": "advanced",
      "sharpe_3y": 1.3922295171388397,
      "sharpe_6m": 0.3252541993923011,
      "is_active": true,
      "updated_at": "2026-03-10T12:06:49.552283"
    },
    "ADV_002700": {
      "file": "ADV_002700.json",
      "asset": "GVSK10YR Index",
      "strategy_type": "advanced",
      "sharpe_3y": 1.0787697523088984,
      "sharpe_6m": -0.09973118455557055,
      "is_active": true,
      "updated_at": "2026-03-10T12:06:49.563284"
    },
    "ADV_002701": {
      "file": "ADV_002701.json",
      "asset": "GVSK10YR Index",
      "strategy_type": "advanced",
      "sharpe_3y": 1.2022053739066345,
      "sharpe_6m": -0.3777518063337637,
      "is_active": true,
      "updated_at": "2026-03-10T12:06:49.574283"
    },
    "ADV_002702": {
      "file": "ADV_002702.json",
      "asset": "GVSK10YR Index",
      "strategy_type": "advanced",
      "sharpe_3y": 1.2610874215994898,
      "sharpe_6m": -0.7144769446928328,
      "is_active": true,
      "updated_at": "2026-03-10T12:06:49.585282"
    },
    "ADV_002703": {
      "file": "ADV_002703.json",
      "asset": "GVSK10YR Index",
      "strategy_type": "advanced",
      "sharpe_3y": 1.2898139384731562,
      "sharpe_6m": -0.10809140675742468,
      "is_active": true,
      "updated_at": "2026-03-10T12:06:49.597284"
    },
    "ADV_002704": {
      "file": "ADV_002704.json",
      "asset": "GVSK10YR Index",
      "strategy_type": "advanced",
      "sharpe_3y": 1.4471563578781146,
      "sharpe_6m": -0.28223037269954254,
      "is_active": true,
      "updated_at": "2026-03-10T12:06:49.608282"
    },
    "ADV_002705": {
      "file": "ADV_002705.json",
      "asset": "GVSK10YR Index",
      "strategy_type": "advanced",
      "sharpe_3y": 1.427075746793627,
      "sharpe_6m": -0.5772901771610592,
      "is_active": true,
      "updated_at": "2026-03-10T12:06:49.619283"
    },
    "ADV_002764": {
      "file": "ADV_002764.json",
      "asset": "GVSK10YR Index",
      "strategy_type": "advanced",
      "sharpe_3y": 1.034559547217078,
      "sharpe_6m": -0.4085702445557646,
      "is_active": true,
      "updated_at": "2026-03-10T12:06:49.630283"
    },
    "ADV_002765": {
      "file": "ADV_002765.json",
      "asset": "GVSK10YR Index",
      "strategy_type": "advanced",
      "sharpe_3y": 1.4153977779315048,
      "sharpe_6m": -0.7183160229699873,
      "is_active": true,
      "updated_at": "2026-03-10T12:06:49.640281"
    },
    "ADV_002790": {
      "file": "ADV_002790.json",
      "asset": "GVSK3YR Index",
      "strategy_type": "advanced",
      "sharpe_3y": 1.2919076869680997,
      "sharpe_6m": -0.3488196579980578,
      "is_active": true,
      "updated_at": "2026-03-10T12:06:49.651282"
    },
    "ADV_002791": {
      "file": "ADV_002791.json",
      "asset": "GVSK3YR Index",
      "strategy_type": "advanced",
      "sharpe_3y": 1.465999542992817,
      "sharpe_6m": 0.4878180360497792,
      "is_active": true,
      "updated_at": "2026-03-10T12:06:49.662286"
    },
    "ADV_002821": {
      "file": "ADV_002821.json",
      "asset": "GVSK10YR Index",
      "strategy_type": "advanced",
      "sharpe_3y": 1.3400877011271177,
      "sharpe_6m": 0.6818608025393554,
      "is_active": true,
      "updated_at": "2026-03-10T12:06:49.673284"
    },
    "ADV_002825": {
      "file": "ADV_002825.json",
      "asset": "GVSK10YR Index",
      "strategy_type": "advanced",
      "sharpe_3y": 1.2079763055512103,
      "sharpe_6m": 1.266494521156779,
      "is_active": true,
      "updated_at": "2026-03-10T12:06:49.685284"
    },
    "ADV_002828": {
      "file": "ADV_002828.json",
      "asset": "GVSK10YR Index",
      "strategy_type": "advanced",
      "sharpe_3y": 1.0644830791289677,
      "sharpe_6m": -0.3501875083690737,
      "is_active": true,
      "updated_at": "2026-03-10T12:06:49.698284"
    },
    "ADV_002976": {
      "file": "ADV_002976.json",
      "asset": "GVSK3YR Index",
      "strategy_type": "advanced",
      "sharpe_3y": 1.190434468130037,
      "sharpe_6m": -2.1077021439377455,
      "is_active": true,
      "updated_at": "2026-03-10T12:06:49.709284"
    },
    "ADV_002977": {
      "file": "ADV_002977.json",
      "asset": "GVSK3YR Index",
      "strategy_type": "advanced",
      "sharpe_3y": 1.4495773922038468,
      "sharpe_6m": -1.3016659831643203,
      "is_active": true,
      "updated_at": "2026-03-10T12:06:49.722286"
    },
    "ADV_002978": {
      "file": "ADV_002978.json",
      "asset": "GVSK3YR Index",
      "strategy_type": "advanced",
      "sharpe_3y": 1.7283114289325014,
      "sharpe_6m": 0.009525637835498332,
      "is_active": true,
      "updated_at": "2026-03-10T12:06:49.733287"
    },
    "ADV_002980": {
      "file": "ADV_002980.json",
      "asset": "GVSK3YR Index",
      "strategy_type": "advanced",
      "sharpe_3y": 1.3930646297681297,
      "sharpe_6m": -0.5691263684887852,
      "is_active": true,
      "updated_at": "2026-03-10T12:06:49.744282"
    },
    "ADV_002981": {
      "file": "ADV_002981.json",
      "asset": "GVSK3YR Index",
      "strategy_type": "advanced",
      "sharpe_3y": 1.1787194948231432,
      "sharpe_6m": -0.5381432808189798,
      "is_active": true,
      "updated_at": "2026-03-10T12:06:49.756282"
    },
    "ADV_002984": {
      "file": "ADV_002984.json",
      "asset": "GVSK3YR Index",
      "strategy_type": "advanced",
      "sharpe_3y": 1.2417151622675027,
      "sharpe_6m": -0.7088855646989086,
      "is_active": true,
      "updated_at": "2026-03-10T12:06:49.769283"
    },
    "ADV_003026": {
      "file": "ADV_003026.json",
      "asset": "GVSK10YR Index",
      "strategy_type": "advanced",
      "sharpe_3y": 1.0842063720029886,
      "sharpe_6m": -0.1416036761415866,
      "is_active": true,
      "updated_at": "2026-03-10T12:07:39.360347"
    },
    "ADV_003029": {
      "file": "ADV_003029.json",
      "asset": "GVSK10YR Index",
      "strategy_type": "advanced",
      "sharpe_3y": 1.1012250570007152,
      "sharpe_6m": 0.47703756431436806,
      "is_active": true,
      "updated_at": "2026-03-10T12:07:39.375349"
    },
    "ADV_003103": {
      "file": "ADV_003103.json",
      "asset": "GVSK3YR Index",
      "strategy_type": "advanced",
      "sharpe_3y": 1.3803389095867589,
      "sharpe_6m": 1.621610710490076,
      "is_active": true,
      "updated_at": "2026-03-10T12:07:39.388348"
    },
    "ADV_003104": {
      "file": "ADV_003104.json",
      "asset": "GVSK3YR Index",
      "strategy_type": "advanced",
      "sharpe_3y": 1.3452554663596,
      "sharpe_6m": 0.4495110408885717,
      "is_active": true,
      "updated_at": "2026-03-10T12:07:39.401348"
    },
    "ADV_003106": {
      "file": "ADV_003106.json",
      "asset": "GVSK3YR Index",
      "strategy_type": "advanced",
      "sharpe_3y": 1.4529296752892127,
      "sharpe_6m": -0.6225185719740942,
      "is_active": true,
      "updated_at": "2026-03-10T12:07:39.412350"
    },
    "ADV_003107": {
      "file": "ADV_003107.json",
      "asset": "GVSK3YR Index",
      "strategy_type": "advanced",
      "sharpe_3y": 1.713971682807592,
      "sharpe_6m": 0.713730635044937,
      "is_active": true,
      "updated_at": "2026-03-10T12:07:39.425348"
    }
  },
  "last_updated": "2026-03-10T16:45:26.418075"
}