{
  "strategy_id": "MR_001827",
  "created_at": "2026-03-10T12:05:53.444209",
  "updated_at": "2026-03-10T12:05:53.451211",
  "asset": "JB1 Comdty",
  "strategy_type": "mean_reversion",
  "strategy_name": "spread_zscore_reversion",
  "params": {
    "period": 10,
    "entry_threshold": 1.5,
    "exit_threshold": 0.5
  },
  "related_asset": "TY1 Comdty",
  "performance": {
    "sharpe_3y": 2.5360584664689725,
    "sharpe_6m": 1.8521006852767679,
    "sharpe_1m": 3.7670981732177995,
    "total_return": 0.24867878670168395,
    "annual_return": 0.0,
    "max_drawdown": 0.022971774084656227,
    "win_rate": 0.7272727272727273,
    "num_trades": 133,
    "calmar_ratio": 3.0085061532053907,
    "sortino_ratio": 5.41041587325409
  },
  "is_active": true,
  "version": 1
}