{
  "strategy_id": "MR_001833",
  "created_at": "2026-03-10T11:58:24.068008",
  "updated_at": "2026-03-10T11:58:24.074008",
  "asset": "JB1 Comdty",
  "strategy_type": "mean_reversion",
  "strategy_name": "spread_zscore_reversion",
  "params": {
    "period": 20,
    "entry_threshold": 1.5,
    "exit_threshold": 0.5
  },
  "related_asset": "TY1 Comdty",
  "performance": {
    "sharpe_3y": 1.5653574691524068,
    "sharpe_6m": 0.017321462394710933,
    "sharpe_1m": -1.1220458477965707,
    "total_return": 0.120671042463767,
    "annual_return": 0.0,
    "max_drawdown": 0.036148161795349236,
    "win_rate": 0.7236842105263157,
    "num_trades": 77,
    "calmar_ratio": 1.0026441967705422,
    "sortino_ratio": 2.4221488357825414
  },
  "is_active": true,
  "version": 1
}