{
  "strategy_id": "ADV_002696",
  "created_at": "2026-03-10T12:10:34.692136",
  "updated_at": "2026-03-10T12:10:34.700136",
  "asset": "GVSK3YR Index",
  "strategy_type": "advanced",
  "strategy_name": "lead_lag_momentum",
  "params": {
    "period": 20,
    "threshold": 1.0
  },
  "related_asset": "GVSK10YR Index",
  "performance": {
    "sharpe_3y": 1.175981240095942,
    "sharpe_6m": -0.09135150167824337,
    "sharpe_1m": -3.279014975839749,
    "total_return": 1.1716466659806013,
    "annual_return": 0.0,
    "max_drawdown": 0.3473616523598623,
    "win_rate": 0.425,
    "num_trades": 40,
    "calmar_ratio": 0.7422155901621297,
    "sortino_ratio": 1.5088136920836468
  },
  "is_active": true,
  "version": 1
}