{
  "strategy_id": "MR_001825",
  "created_at": "2026-03-10T13:00:30.610878",
  "updated_at": "2026-03-10T13:00:30.616879",
  "asset": "JB1 Comdty",
  "strategy_type": "mean_reversion",
  "strategy_name": "spread_zscore_reversion",
  "params": {
    "period": 10,
    "entry_threshold": 1.0,
    "exit_threshold": 0.5
  },
  "related_asset": "TY1 Comdty",
  "performance": {
    "sharpe_3y": 1.8867754055701575,
    "sharpe_6m": 0.8387365270051061,
    "sharpe_1m": 2.4624459127440685,
    "total_return": 0.3471866698841879,
    "annual_return": 0.0,
    "max_drawdown": 0.029061292132050647,
    "win_rate": 0.6598360655737704,
    "num_trades": 245,
    "calmar_ratio": 2.52351481308905,
    "sortino_ratio": 4.609836951052151
  },
  "is_active": true,
  "version": 1
}