{
  "strategy_id": "MR_002189",
  "created_at": "2026-03-10T12:32:28.394801",
  "updated_at": "2026-03-10T12:32:28.399801",
  "asset": "JB1 Comdty",
  "strategy_type": "mean_reversion",
  "strategy_name": "spread_percentile_reversion",
  "params": {
    "period": 20,
    "low_percentile": 20,
    "high_percentile": 90,
    "exit_percentile": 50
  },
  "related_asset": "TY1 Comdty",
  "performance": {
    "sharpe_3y": 1.289433354780545,
    "sharpe_6m": 0.9414741762411979,
    "sharpe_1m": -2.461575359835023,
    "total_return": 0.13103471896434202,
    "annual_return": 0.0,
    "max_drawdown": 0.04155961903626522,
    "win_rate": 0.5882352941176471,
    "num_trades": 86,
    "calmar_ratio": 0.8066393747927424,
    "sortino_ratio": 1.8883081393400105
  },
  "is_active": true,
  "version": 1
}