{
  "strategies": {
    "MOM_000038": {
      "file": "MOM_000038.json",
      "asset": "NQ1 Index",
      "strategy_type": "momentum",
      "sharpe_3y": 1.0952302291096518,
      "sharpe_6m": 3.1164832032531185,
      "is_active": true,
      "updated_at": "2026-03-10T12:55:58.552558"
    },
    "MOM_000132": {
      "file": "MOM_000132.json",
      "asset": "NQ1 Index",
      "strategy_type": "momentum",
      "sharpe_3y": 1.1174869269700611,
      "sharpe_6m": 3.3965228252182973,
      "is_active": true,
      "updated_at": "2026-03-10T12:55:58.563558"
    },
    "MOM_000133": {
      "file": "MOM_000133.json",
      "asset": "NQ1 Index",
      "strategy_type": "momentum",
      "sharpe_3y": 1.47126591382079,
      "sharpe_6m": 3.799155048742086,
      "is_active": true,
      "updated_at": "2026-03-10T12:55:58.576556"
    },
    "MOM_000134": {
      "file": "MOM_000134.json",
      "asset": "NQ1 Index",
      "strategy_type": "momentum",
      "sharpe_3y": 1.3023339162368481,
      "sharpe_6m": 3.7991550487420853,
      "is_active": true,
      "updated_at": "2026-03-10T12:55:58.584558"
    },
    "MOM_000135": {
      "file": "MOM_000135.json",
      "asset": "NQ1 Index",
      "strategy_type": "momentum",
      "sharpe_3y": 1.3291196199529045,
      "sharpe_6m": 3.7832639475190697,
      "is_active": true,
      "updated_at": "2026-03-10T12:55:58.594557"
    },
    "MOM_000136": {
      "file": "MOM_000136.json",
      "asset": "NQ1 Index",
      "strategy_type": "momentum",
      "sharpe_3y": 1.3206354552798734,
      "sharpe_6m": 3.799155048742084,
      "is_active": true,
      "updated_at": "2026-03-10T12:55:58.604559"
    },
    "MOM_000137": {
      "file": "MOM_000137.json",
      "asset": "NQ1 Index",
      "strategy_type": "momentum",
      "sharpe_3y": 1.236716926769108,
      "sharpe_6m": 3.6521634887626444,
      "is_active": true,
      "updated_at": "2026-03-10T12:55:58.612556"
    },
    "MOM_000221": {
      "file": "MOM_000221.json",
      "asset": "NQ1 Index",
      "strategy_type": "momentum",
      "sharpe_3y": 1.086251454976276,
      "sharpe_6m": 3.1247885536598314,
      "is_active": true,
      "updated_at": "2026-03-10T12:55:58.621559"
    },
    "MOM_000452": {
      "file": "MOM_000452.json",
      "asset": "NQ1 Index",
      "strategy_type": "momentum",
      "sharpe_3y": 1.1504262411144515,
      "sharpe_6m": 2.965848971446758,
      "is_active": true,
      "updated_at": "2026-03-10T12:55:58.629556"
    },
    "MOM_000460": {
      "file": "MOM_000460.json",
      "asset": "NQ1 Index",
      "strategy_type": "momentum",
      "sharpe_3y": 1.0089481154320465,
      "sharpe_6m": 2.5092241874433543,
      "is_active": true,
      "updated_at": "2026-03-10T12:55:58.638558"
    },
    "MOM_000461": {
      "file": "MOM_000461.json",
      "asset": "NQ1 Index",
      "strategy_type": "momentum",
      "sharpe_3y": 1.0154427145924037,
      "sharpe_6m": 2.2454688193354184,
      "is_active": true,
      "updated_at": "2026-03-10T12:55:58.645557"
    },
    "MOM_000893": {
      "file": "MOM_000893.json",
      "asset": "NQ1 Index",
      "strategy_type": "momentum",
      "sharpe_3y": 1.1079664583863902,
      "sharpe_6m": 2.910295165473555,
      "is_active": true,
      "updated_at": "2026-03-10T12:55:58.653559"
    },
    "MR_000939": {
      "file": "MR_000939.json",
      "asset": "G 1 Comdty",
      "strategy_type": "mean_reversion",
      "sharpe_3y": 1.1749472883478391,
      "sharpe_6m": 1.4092421791966705,
      "is_active": true,
      "updated_at": "2026-03-10T12:55:58.661558"
    },
    "MR_001485": {
      "file": "MR_001485.json",
      "asset": "BP1 Curncy",
      "strategy_type": "mean_reversion",
      "sharpe_3y": 1.3282840600894872,
      "sharpe_6m": 3.6861971516717604,
      "is_active": true,
      "updated_at": "2026-03-10T12:56:53.809626"
    },
    "MR_001824": {
      "file": "MR_001824.json",
      "asset": "JB1 Comdty",
      "strategy_type": "mean_reversion",
      "sharpe_3y": 1.734885861204082,
      "sharpe_6m": 1.7062234995140697,
      "is_active": true,
      "updated_at": "2026-03-10T12:56:53.819629"
    },
    "MR_001825": {
      "file": "MR_001825.json",
      "asset": "JB1 Comdty",
      "strategy_type": "mean_reversion",
      "sharpe_3y": 1.8572091159401132,
      "sharpe_6m": 1.1862502279383202,
      "is_active": true,
      "updated_at": "2026-03-10T12:56:53.826626"
    },
    "MR_001826": {
      "file": "MR_001826.json",
      "asset": "JB1 Comdty",
      "strategy_type": "mean_reversion",
      "sharpe_3y": 1.571748860790522,
      "sharpe_6m": 1.327484105844622,
      "is_active": true,
      "updated_at": "2026-03-10T12:56:53.835628"
    },
    "MR_001827": {
      "file": "MR_001827.json",
      "asset": "JB1 Comdty",
      "strategy_type": "mean_reversion",
      "sharpe_3y": 1.9694320917047725,
      "sharpe_6m": 1.8201571952224835,
      "is_active": true,
      "updated_at": "2026-03-10T12:56:53.844626"
    },
    "MR_001828": {
      "file": "MR_001828.json",
      "asset": "JB1 Comdty",
      "strategy_type": "mean_reversion",
      "sharpe_3y": 1.3335993005520148,
      "sharpe_6m": 0.3510099027424422,
      "is_active": true,
      "updated_at": "2026-03-10T12:56:53.855627"
    },
    "MR_001829": {
      "file": "MR_001829.json",
      "asset": "JB1 Comdty",
      "strategy_type": "mean_reversion",
      "sharpe_3y": 1.5009648963698774,
      "sharpe_6m": 0.7119759789542763,
      "is_active": true,
      "updated_at": "2026-03-10T12:56:53.866628"
    },
    "MR_001830": {
      "file": "MR_001830.json",
      "asset": "JB1 Comdty",
      "strategy_type": "mean_reversion",
      "sharpe_3y": 1.1797998417687452,
      "sharpe_6m": 0.11263803429559945,
      "is_active": true,
      "updated_at": "2026-03-10T12:56:53.877626"
    },
    "MR_001831": {
      "file": "MR_001831.json",
      "asset": "JB1 Comdty",
      "strategy_type": "mean_reversion",
      "sharpe_3y": 1.1349549765543407,
      "sharpe_6m": 0.6717842709777666,
      "is_active": true,
      "updated_at": "2026-03-10T12:56:53.888627"
    },
    "MR_001833": {
      "file": "MR_001833.json",
      "asset": "JB1 Comdty",
      "strategy_type": "mean_reversion",
      "sharpe_3y": 1.0114432501186146,
      "sharpe_6m": 0.576705386402536,
      "is_active": true,
      "updated_at": "2026-03-10T12:56:53.900627"
    },
    "MR_001834": {
      "file": "MR_001834.json",
      "asset": "JB1 Comdty",
      "strategy_type": "mean_reversion",
      "sharpe_3y": 1.0027215585261098,
      "sharpe_6m": -0.8643978664969189,
      "is_active": true,
      "updated_at": "2026-03-10T12:56:53.913629"
    },
    "MR_001837": {
      "file": "MR_001837.json",
      "asset": "JB1 Comdty",
      "strategy_type": "mean_reversion",
      "sharpe_3y": 1.0427613906048128,
      "sharpe_6m": -0.5477316296695175,
      "is_active": true,
      "updated_at": "2026-03-10T12:56:53.924628"
    },
    "MR_002049": {
      "file": "MR_002049.json",
      "asset": "RX1 Comdty",
      "strategy_type": "mean_reversion",
      "sharpe_3y": 1.482113795284318,
      "sharpe_6m": 2.6307638147033403,
      "is_active": true,
      "updated_at": "2026-03-10T12:57:48.743637"
    },
    "MR_002050": {
      "file": "MR_002050.json",
      "asset": "RX1 Comdty",
      "strategy_type": "mean_reversion",
      "sharpe_3y": 1.3642822212115608,
      "sharpe_6m": 2.630763814703327,
      "is_active": true,
      "updated_at": "2026-03-10T12:57:48.755638"
    },
    "MR_002067": {
      "file": "MR_002067.json",
      "asset": "RX1 Comdty",
      "strategy_type": "mean_reversion",
      "sharpe_3y": 1.0790487092991319,
      "sharpe_6m": -0.10669523164999949,
      "is_active": true,
      "updated_at": "2026-03-10T12:57:48.763641"
    },
    "MR_002068": {
      "file": "MR_002068.json",
      "asset": "RX1 Comdty",
      "strategy_type": "mean_reversion",
      "sharpe_3y": 1.1385072844274233,
      "sharpe_6m": -0.0690277495327814,
      "is_active": true,
      "updated_at": "2026-03-10T12:57:48.772639"
    },
    "MR_002073": {
      "file": "MR_002073.json",
      "asset": "RX1 Comdty",
      "strategy_type": "mean_reversion",
      "sharpe_3y": 1.1667218553467034,
      "sharpe_6m": -0.33249890504377905,
      "is_active": true,
      "updated_at": "2026-03-10T12:57:48.781638"
    },
    "MR_002074": {
      "file": "MR_002074.json",
      "asset": "RX1 Comdty",
      "strategy_type": "mean_reversion",
      "sharpe_3y": 1.2227037747655318,
      "sharpe_6m": -0.302505428031014,
      "is_active": true,
      "updated_at": "2026-03-10T12:57:48.789638"
    },
    "MR_002075": {
      "file": "MR_002075.json",
      "asset": "RX1 Comdty",
      "strategy_type": "mean_reversion",
      "sharpe_3y": 1.068471356759729,
      "sharpe_6m": -0.27199230718737205,
      "is_active": true,
      "updated_at": "2026-03-10T12:57:48.798637"
    },
    "MR_002184": {
      "file": "MR_002184.json",
      "asset": "JB1 Comdty",
      "strategy_type": "mean_reversion",
      "sharpe_3y": 1.1405870259768995,
      "sharpe_6m": 0.6427399335434204,
      "is_active": true,
      "updated_at": "2026-03-10T12:57:48.807637"
    },
    "MR_002185": {
      "file": "MR_002185.json",
      "asset": "JB1 Comdty",
      "strategy_type": "mean_reversion",
      "sharpe_3y": 1.1660620393733416,
      "sharpe_6m": 0.5234707121879761,
      "is_active": true,
      "updated_at": "2026-03-10T12:57:48.815637"
    },
    "MR_002186": {
      "file": "MR_002186.json",
      "asset": "JB1 Comdty",
      "strategy_type": "mean_reversion",
      "sharpe_3y": 1.017469646556639,
      "sharpe_6m": 0.07463399225132492,
      "is_active": true,
      "updated_at": "2026-03-10T12:57:48.824639"
    },
    "MR_002187": {
      "file": "MR_002187.json",
      "asset": "JB1 Comdty",
      "strategy_type": "mean_reversion",
      "sharpe_3y": 1.1137331756448847,
      "sharpe_6m": 0.3297408645728305,
      "is_active": true,
      "updated_at": "2026-03-10T12:57:48.837640"
    },
    "MR_002188": {
      "file": "MR_002188.json",
      "asset": "JB1 Comdty",
      "strategy_type": "mean_reversion",
      "sharpe_3y": 1.1381086622461307,
      "sharpe_6m": 0.2246398745500918,
      "is_active": true,
      "updated_at": "2026-03-10T12:57:48.845637"
    },
    "MR_002190": {
      "file": "MR_002190.json",
      "asset": "JB1 Comdty",
      "strategy_type": "mean_reversion",
      "sharpe_3y": 1.1192527834037667,
      "sharpe_6m": 0.4749460307921654,
      "is_active": true,
      "updated_at": "2026-03-10T12:57:48.854639"
    },
    "MR_002191": {
      "file": "MR_002191.json",
      "asset": "JB1 Comdty",
      "strategy_type": "mean_reversion",
      "sharpe_3y": 1.1433681146246655,
      "sharpe_6m": 0.3725007795132572,
      "is_active": true,
      "updated_at": "2026-03-10T12:57:48.862637"
    },
    "MR_002199": {
      "file": "MR_002199.json",
      "asset": "JB1 Comdty",
      "strategy_type": "mean_reversion",
      "sharpe_3y": 1.0336000211760907,
      "sharpe_6m": -0.09663196913873716,
      "is_active": true,
      "updated_at": "2026-03-10T12:57:48.872641"
    },
    "ADV_002386": {
      "file": "ADV_002386.json",
      "asset": "NQ1 Index",
      "strategy_type": "advanced",
      "sharpe_3y": 1.288504643167927,
      "sharpe_6m": 2.9597042598947634,
      "is_active": true,
      "updated_at": "2026-03-10T12:57:48.881640"
    },
    "ADV_002389": {
      "file": "ADV_002389.json",
      "asset": "NQ1 Index",
      "strategy_type": "advanced",
      "sharpe_3y": 1.2324656403479264,
      "sharpe_6m": 2.92030970433149,
      "is_active": true,
      "updated_at": "2026-03-10T12:57:48.890641"
    },
    "ADV_002390": {
      "file": "ADV_002390.json",
      "asset": "NQ1 Index",
      "strategy_type": "advanced",
      "sharpe_3y": 1.0753616830128476,
      "sharpe_6m": 2.710024589254781,
      "is_active": true,
      "updated_at": "2026-03-10T12:57:48.899637"
    },
    "ADV_002399": {
      "file": "ADV_002399.json",
      "asset": "NQ1 Index",
      "strategy_type": "advanced",
      "sharpe_3y": 1.082496935957143,
      "sharpe_6m": 2.7100245892547807,
      "is_active": true,
      "updated_at": "2026-03-10T12:57:48.908638"
    },
    "ADV_002774": {
      "file": "ADV_002774.json",
      "asset": "NQ1 Index",
      "strategy_type": "advanced",
      "sharpe_3y": 1.2129385169419287,
      "sharpe_6m": 2.970552632780498,
      "is_active": true,
      "updated_at": "2026-03-10T12:57:48.918640"
    },
    "ADV_002881": {
      "file": "ADV_002881.json",
      "asset": "NQ1 Index",
      "strategy_type": "advanced",
      "sharpe_3y": 1.3110790698642754,
      "sharpe_6m": 3.4413679968067696,
      "is_active": true,
      "updated_at": "2026-03-10T12:57:48.929638"
    },
    "ADV_002885": {
      "file": "ADV_002885.json",
      "asset": "NQ1 Index",
      "strategy_type": "advanced",
      "sharpe_3y": 1.021269935907224,
      "sharpe_6m": 2.9710681938335033,
      "is_active": true,
      "updated_at": "2026-03-10T12:57:48.941639"
    },
    "ADV_003056": {
      "file": "ADV_003056.json",
      "asset": "NQ1 Index",
      "strategy_type": "advanced",
      "sharpe_3y": 1.1509076282864432,
      "sharpe_6m": 1.6655970977320604,
      "is_active": true,
      "updated_at": "2026-03-10T12:58:34.647168"
    }
  },
  "last_updated": "2026-03-10T14:03:13.745265"
}