{
  "strategy_id": "MR_002187",
  "created_at": "2026-02-24T12:22:44.234108",
  "updated_at": "2026-02-26T16:47:28.682871",
  "asset": "GJGB10 Index",
  "strategy_type": "mean_reversion",
  "strategy_name": "spread_percentile_reversion",
  "params": {
    "period": 20,
    "low_percentile": 20,
    "high_percentile": 75,
    "exit_percentile": 50
  },
  "related_asset": "USGG10YR Index",
  "performance": {
    "sharpe_3y": 1.5167895818295776,
    "sharpe_6m": -0.7831473953364271,
    "sharpe_1m": -0.3142901454784747,
    "total_return": 0.23423268582683335,
    "annual_return": 0.0,
    "max_drawdown": 0.03857089630334133,
    "win_rate": 0.580952380952381,
    "num_trades": 105,
    "calmar_ratio": 1.3420591160171784,
    "sortino_ratio": 2.2380056281641565
  },
  "is_active": true,
  "version": 1
}