{
  "strategy_id": "MR_002185",
  "created_at": "2026-03-10T13:08:58.822275",
  "updated_at": "2026-03-10T13:08:58.827276",
  "asset": "JB1 Comdty",
  "strategy_type": "mean_reversion",
  "strategy_name": "spread_percentile_reversion",
  "params": {
    "period": 20,
    "low_percentile": 10,
    "high_percentile": 80,
    "exit_percentile": 50
  },
  "related_asset": "TY1 Comdty",
  "performance": {
    "sharpe_3y": 1.2716777778133956,
    "sharpe_6m": -1.5721014028824958,
    "sharpe_1m": -0.030690348845097772,
    "total_return": 0.16568283228894218,
    "annual_return": 0.0,
    "max_drawdown": 0.041539720473776034,
    "win_rate": 0.6,
    "num_trades": 100,
    "calmar_ratio": 0.867296866790537,
    "sortino_ratio": 1.970913001409556
  },
  "is_active": true,
  "version": 1
}