{
  "strategy_id": "MR_001835",
  "created_at": "2026-03-10T11:51:10.631461",
  "updated_at": "2026-03-10T11:51:10.639462",
  "asset": "JB1 Comdty",
  "strategy_type": "mean_reversion",
  "strategy_name": "spread_zscore_reversion",
  "params": {
    "period": 20,
    "entry_threshold": 2.0,
    "exit_threshold": 0.5
  },
  "related_asset": "TY1 Comdty",
  "performance": {
    "sharpe_3y": 1.2215719758497565,
    "sharpe_6m": 1.0830819794699498,
    "sharpe_1m": 3.829863507000992,
    "total_return": 0.07155629004696251,
    "annual_return": 0.0,
    "max_drawdown": 0.03675595302538757,
    "win_rate": 0.7142857142857143,
    "num_trades": 42,
    "calmar_ratio": 0.616942575051746,
    "sortino_ratio": 1.6257765231242367
  },
  "is_active": true,
  "version": 1
}