{
  "strategy_id": "MR_010659",
  "created_at": "2026-02-13T14:31:36.692320",
  "updated_at": "2026-02-13T14:31:58.822383",
  "asset": "GTAUD3YR Corp",
  "strategy_type": "mean_reversion",
  "strategy_name": "spread_zscore_reversion",
  "params": {
    "period": 10,
    "entry_threshold": 1.5,
    "exit_threshold": 0.5
  },
  "related_asset": "JPY Curncy",
  "performance": {
    "sharpe_3y": 1.2227729486045766,
    "sharpe_6m": 3.2519133172174577,
    "sharpe_1m": 0,
    "total_return": 0,
    "annual_return": 0,
    "max_drawdown": 0,
    "win_rate": 0,
    "num_trades": 20,
    "calmar_ratio": 0,
    "sortino_ratio": 0
  },
  "is_active": true,
  "version": 1
}