{
  "strategy_id": "MR_001825",
  "created_at": "2026-03-10T12:38:48.323001",
  "updated_at": "2026-03-10T12:38:48.332004",
  "asset": "JB1 Comdty",
  "strategy_type": "mean_reversion",
  "strategy_name": "spread_zscore_reversion",
  "params": {
    "period": 10,
    "entry_threshold": 1.0,
    "exit_threshold": 0.5
  },
  "related_asset": "TY1 Comdty",
  "performance": {
    "sharpe_3y": 2.451567704976257,
    "sharpe_6m": 1.32519464337231,
    "sharpe_1m": 5.010281755115215,
    "total_return": 0.3353078190404875,
    "annual_return": 0.0,
    "max_drawdown": 0.029061292132050647,
    "win_rate": 0.6666666666666665,
    "num_trades": 223,
    "calmar_ratio": 2.6804989091338998,
    "sortino_ratio": 5.0737390458450164
  },
  "is_active": true,
  "version": 1
}