{
  "strategy_id": "ADV_002730",
  "created_at": "2026-02-19T15:53:28.739672",
  "updated_at": "2026-02-19T15:53:28.755488",
  "asset": "GJGB10 Index",
  "strategy_type": "advanced",
  "strategy_name": "lead_lag_momentum",
  "params": {
    "period": 20,
    "threshold": 0
  },
  "related_asset": "USGG10YR Index",
  "performance": {
    "sharpe_3y": 1.8291322242385655,
    "sharpe_6m": 2.6467616769338083,
    "sharpe_1m": 0.7784244053095917,
    "total_return": 0.20562728444952838,
    "annual_return": 0.0,
    "max_drawdown": 0.015577397488072423,
    "win_rate": 0.5060240963855421,
    "num_trades": 83,
    "calmar_ratio": 2.797794944551429,
    "sortino_ratio": 2.795557946665171
  },
  "is_active": true,
  "version": 1
}